venus/__init__.py
venus/context.py
venus/exception.py
venus/i18n.py
venus/manager.py
venus/rpc.py
venus/service.py
venus/utils.py
venus/version.py
venus/api/__init__.py
venus/api/common.py
venus/api/extensions.py
venus/api/urlmap.py
venus/api/xmlutil.py
venus/api/contrib/__init__.py
venus/api/middleware/__init__.py
venus/api/middleware/auth.py
venus/api/middleware/env.py
venus/api/middleware/fault.py
venus/api/middleware/sizelimit.py
venus/api/openstack/__init__.py
venus/api/openstack/wsgi.py
venus/api/schemas/atom-link.rng
venus/api/schemas/v1.1/extension.rng
venus/api/schemas/v1.1/extensions.rng
venus/api/v1/__init__.py
venus/api/v1/router.py
venus/api/v1/views/__init__.py
venus/api/v1/views/versions.py
venus/cmd/__init__.py
venus/cmd/api.py
venus/cmd/manage.py
venus/cmd/task.py
venus/common/__init__.py
venus/common/utils.py
venus/conf/__init__.py
venus/conf/api.py
venus/conf/common.py
venus/conf/core.py
venus/conf/db.py
venus/conf/elasticsearch.py
venus/conf/profiler.py
venus/db/__init__.py
venus/db/alembic.ini
venus/db/api.py
venus/db/base.py
venus/db/migration.py
venus/db/alembic/README
venus/db/alembic/env.py
venus/db/alembic/script.py.mako
venus/db/alembic/versions/a6cf98f55b4d_.py
venus/db/alembic/versions/a6cf98f55b4e_.py
venus/hacking/__init__.py
venus/hacking/checks.py
venus/locale/venus-log-info.pot
venus/locale/venus-log-warning.pot
venus/locale/venus.pot
venus/modules/__init__.py
venus/modules/anomaly_detect/__init__.py
venus/modules/anomaly_detect/action.py
venus/modules/anomaly_detect/controller.py
venus/modules/anomaly_detect/backends/__init__.py
venus/modules/anomaly_detect/backends/models.py
venus/modules/anomaly_detect/backends/sql.py
venus/modules/custom_config/__init__.py
venus/modules/custom_config/action.py
venus/modules/custom_config/controller.py
venus/modules/custom_config/backends/__init__.py
venus/modules/custom_config/backends/models.py
venus/modules/custom_config/backends/sql.py
venus/modules/search/__init__.py
openstack_venus-7.0.0.dist-info/AUTHORS
openstack_venus-7.0.0.dist-info/LICENSE
openstack_venus-7.0.0.dist-info/METADATA
openstack_venus-7.0.0.dist-info/WHEEL
openstack_venus-7.0.0.dist-info/entry_points.txt
openstack_venus-7.0.0.dist-info/pbr.json
openstack_venus-7.0.0.dist-info/top_level.txt
openstack_venus-7.0.0.dist-info/RECORD
