Metadata-Version: 2.1
Name: openstack-venus
Version: 7.0.0
Summary: OpenStack Log Management as a Service
Author: Brin Zhang
Author-email: zhangbailin@inspur.com
Classifier: Environment :: OpenStack
Classifier: Intended Audience :: Information Technology
Classifier: Intended Audience :: System Administrators
Classifier: License :: OSI Approved :: Apache Software License
Classifier: Operating System :: POSIX :: Linux
Classifier: Programming Language :: Python
Classifier: Programming Language :: Python :: Implementation :: CPython
Classifier: Programming Language :: Python :: 3 :: Only
Classifier: Programming Language :: Python :: 3
Classifier: Programming Language :: Python :: 3.8
Classifier: Programming Language :: Python :: 3.9
Classifier: Programming Language :: Python :: 3.10
Classifier: Programming Language :: Python :: 3.11
Requires-Python: >=3.8
License-File: LICENSE
License-File: AUTHORS
Requires-Dist: pbr !=2.1.0,>=0.11
Requires-Dist: pecan !=1.0.2,!=1.0.3,!=1.0.4,!=1.2,>=1.0.0
Requires-Dist: WSME >=0.10.1
Requires-Dist: eventlet >=0.26.0
Requires-Dist: oslo.i18n >=1.5.0
Requires-Dist: oslo.context >=2.9.0
Requires-Dist: oslo.messaging >=10.3.0
Requires-Dist: oslo.concurrency >=3.26.0
Requires-Dist: oslo.service !=1.28.1,>=1.0.0
Requires-Dist: oslo.db >=10.0.0
Requires-Dist: os-resource-classes >=0.5.0
Requires-Dist: oslo.upgradecheck >=0.1.0
Requires-Dist: oslo.utils >=4.5.0
Requires-Dist: oslo.versionedobjects >=1.31.2
Requires-Dist: osprofiler >=3.4.0
Requires-Dist: SQLAlchemy >=1.4.0
Requires-Dist: alembic >=0.8.10
Requires-Dist: stevedore >=1.5.0
Requires-Dist: keystonemiddleware >=4.17.0
Requires-Dist: jsonpatch !=1.20,>=1.16
Requires-Dist: psutil >=3.2.2
Requires-Dist: python-glanceclient >=2.3.0
Requires-Dist: cursive >=0.2.1
Requires-Dist: microversion-parse >=0.2.1
Requires-Dist: openstacksdk >=0.46.0
Requires-Dist: elasticsearch <3.0.0,>=2.0.0
Requires-Dist: apscheduler >=3.6.0
Requires-Dist: retrying >=1.3.3
Requires-Dist: lxml >=4.6.2
Requires-Dist: PyMySQL >=0.7.11
Requires-Dist: oslo.log >=4.2.1 ; (python_version=='3.6')
Requires-Dist: oslo.log >=4.2.1 ; (python_version=='3.7')
Requires-Dist: oslo.log >=5.0.0 ; (python_version=='3.8')
